bsa/__init__.py
bsa/branches.py
bsa/instrumentation.py
bsa/kripke.py
bsa/py.typed
branch_statement_analyzer-1.0.0.dist-info/LICENSE.txt
branch_statement_analyzer-1.0.0.dist-info/METADATA
branch_statement_analyzer-1.0.0.dist-info/WHEEL
branch_statement_analyzer-1.0.0.dist-info/RECORD
