Metadata-Version: 2.1
Name: branch-statement-analyzer
Version: 1.0.0
Summary: Branch statement analysis and state decomposition for Python 3.8+
License: BSD-3-Clause
Author: Quinn Thibeault
Author-email: quinn.thibeault96@gmail.com
Requires-Python: >=3.9
Classifier: License :: OSI Approved :: BSD License
Classifier: Programming Language :: Python :: 3
Classifier: Programming Language :: Python :: 3.9
Classifier: Programming Language :: Python :: 3.10
Classifier: Programming Language :: Python :: 3.11
Requires-Dist: typing-extensions (>=4.3.0,<5.0.0)
